[{"url":"https://www.photopea.com/","savedElements":[{"selector":".theme0 > .flexrow > div:nth-child(2)","permanent":true},{"selector":".panelblock > .block > div:nth-child(2)","permanent":true},{"selector":".flexrow .flexrow","permanent":true},{"selector":".body > .fitem:nth-child(2) > .flabel","permanent":true}],"settings":{"remember":true},"id":233},{"url":"https://www.google.com/","savedElements":[{"selector":".k1zIA #hplogo","permanent":true},{"selector":"body .LLD4me","permanent":true},{"selector":"body .qarstb","permanent":true},{"selector":".KxwPGc .ktLKi","permanent":true},{"selector":".o3j99 .ssOUyb","permanent":true},{"selector":".KxwPGc .pHiOh:nth-child(3)","permanent":true},{"selector":".KxwPGc .pHiOh:nth-child(4)","permanent":true},{"selector":".KxwPGc > .iTjxkf > .pHiOh:nth-child(1)","permanent":true},{"selector":".L3eUgb > .o3j99 > .KxwPGc","permanent":true},{"selector":".L3eUgb .uU7dJb","permanent":true}],"settings":{"remember":true},"id":234}]